MANIFEST.in
README.md
setup.cfg
setup.py
dbt/adapters/odps/__init__.py
dbt/adapters/odps/__version__.py
dbt/adapters/odps/colums.py
dbt/adapters/odps/connections.py
dbt/adapters/odps/dbapi.py
dbt/adapters/odps/errors.py
dbt/adapters/odps/impl.py
dbt/adapters/odps/relation.py
dbt/adapters/odps/utils.py
dbt/include/odps/__init__.py
dbt/include/odps/dbt_project.yml
dbt/include/odps/profile_template.yml
dbt/include/odps/macros/adapters.sql
dbt/include/odps/macros/incremental/strategies.sql
dbt/include/odps/macros/snapshots/snapshot.sql
dbt/include/odps/macros/snapshots/strategry.sql
dbt_odps.egg-info/PKG-INFO
dbt_odps.egg-info/SOURCES.txt
dbt_odps.egg-info/dependency_links.txt
dbt_odps.egg-info/requires.txt
dbt_odps.egg-info/top_level.txt